.dada-version
MANIFEST.in
README.md
requirements.txt
setup.cfg
setup.py
dada_types/__init__.py
dada_types/base.py
dada_types/col.py
dada_types/dictionary.py
dada_types/flt.py
dada_types/gen.py
dada_types/hum.py
dada_types/lib.py
dada_types.egg-info/PKG-INFO
dada_types.egg-info/SOURCES.txt
dada_types.egg-info/dependency_links.txt
dada_types.egg-info/requires.txt
dada_types.egg-info/top_level.txt
dada_types/tests/__init__.py
dada_types/tests/test_flt_py.py
dada_types/tests/test_hum.py
dada_types/tests/test_lib.py
dada_types/tests/test_param.py