Metadata-Version: 1.0
Name: dada-types
Version: 0.0.9
Summary: dada-lake's re-usable type library for python/sql/cli contexts
Home-page: http://globally.ltd
Author: gltd
Author-email: hey@gltd.email
License: UNKNOWN
Platform: UNKNOWN
